nark/__init__.py
nark/backends/__init__.py
nark/backends/sqlalchemy/__init__.py
nark/backends/sqlalchemy/managers/__init__.py
nark/backends/sqlalchemy/managers/activity.py
nark/backends/sqlalchemy/managers/category.py
nark/backends/sqlalchemy/managers/fact.py
nark/backends/sqlalchemy/managers/gather_base.py
nark/backends/sqlalchemy/managers/gather_fact.py
nark/backends/sqlalchemy/managers/manager_base.py
nark/backends/sqlalchemy/managers/migrate.py
nark/backends/sqlalchemy/managers/tag.py
nark/backends/sqlalchemy/objects.py
nark/backends/sqlalchemy/storage.py
nark/config/__init__.py
nark/config/log_levels.py
nark/control.py
nark/helpers/__init__.py
nark/helpers/dev/__init__.py
nark/helpers/dev/profiling.py
nark/helpers/fact_time.py
nark/helpers/facts_fit.py
nark/helpers/format_text.py
nark/helpers/format_time.py
nark/helpers/legacy_db.py
nark/helpers/logging.py
nark/helpers/objects.py
nark/helpers/parse_errors.py
nark/helpers/parse_time.py
nark/helpers/parsing.py
nark/helpers/singleton.py
nark/items/__init__.py
nark/items/activity.py
nark/items/category.py
nark/items/fact.py
nark/items/item_base.py
nark/items/tag.py
nark/manager.py
nark/managers/__init__.py
nark/managers/activity.py
nark/managers/category.py
nark/managers/fact.py
nark/managers/migrate.py
nark/managers/query_terms.py
nark/managers/tag.py
nark/migrations/README
nark/migrations/__init__.py
nark/migrations/manage.py
nark/migrations/migrate.cfg.example
nark/migrations/versions/001_Add_deleted_columns.py
nark/migrations/versions/__init__.py
nark/reports/__init__.py
nark/reports/csv_writer.py
nark/reports/ical_writer.py
nark/reports/json_writer.py
nark/reports/plaintext_writer.py
nark/reports/report_writer.py
nark/reports/tsv_writer.py
nark/reports/xml_writer.py
nark/tests/__init__.py
nark/tests/backends/__init__.py
nark/tests/backends/sqlalchemy/__init__.py
nark/tests/backends/sqlalchemy/common.py
nark/tests/backends/sqlalchemy/conftest.py
nark/tests/backends/sqlalchemy/factories.py
nark-3.2.8.dist-info/LICENSE
nark-3.2.8.dist-info/METADATA
nark-3.2.8.dist-info/WHEEL
nark-3.2.8.dist-info/RECORD
