Metadata-Version: 2.1
Name: nark
Version: 3.2.8
Summary: Back end framework for journaling and time tracking apps (like `dob`!)
License: GPLv3+
Keywords: journal,diary,timesheet,timetrack,jrnl,rednotebook,todo.txt,prjct,hamster,fact
Author: Landon Bouma
Author-email: doblabs@tallybark.com
Maintainer: Tally Bark LLC
Maintainer-email: doblabs@tallybark.com
Requires-Python: >=3.8.1,<4.0.0
Classifier: Development Status :: 5 - Production/Stable
Classifier: Intended Audience :: Developers
Classifier: License :: Other/Proprietary License
Classifier: Natural Language :: English
Classifier: Operating System :: OS Independent
Classifier: Programming Language :: Python :: 3
Classifier: Programming Language :: Python :: 3.9
Classifier: Programming Language :: Python :: 3.10
Classifier: Programming Language :: Python :: 3.11
Classifier: Programming Language :: Python :: 3.12
Classifier: Topic :: Software Development :: Libraries :: Python Modules
Provides-Extra: readthedocs
Requires-Dist: ansi-escape-room (>0)
Requires-Dist: ansiwrap-hotoffthehamster (>0)
Requires-Dist: config-decorator (>0)
Requires-Dist: configobj (>=5.0.6,<5.1.0)
Requires-Dist: dateparser (>=1.2.0,<1.3.0)
Requires-Dist: easy-as-pypi-appdirs (>0)
Requires-Dist: easy-as-pypi-getver (>0)
Requires-Dist: human-friendly_pedantic-timedelta (>0)
Requires-Dist: icalendar (>=4.0.5,<4.1.0)
Requires-Dist: iso8601 (>=0.1.12,<0.2.0)
Requires-Dist: lazy_import (>=0.2.2,<0.3.0)
Requires-Dist: pytz (>=2019.3)
Requires-Dist: sphinx (>=6.2.1,<7.0.0) ; (python_version >= "3.8" and python_version < "3.9") and (extra == "readthedocs")
Requires-Dist: sphinx (>=7.2.6,<8.0.0) ; (python_version >= "3.9" and python_version < "4.0") and (extra == "readthedocs")
Requires-Dist: sphinx-rtd-theme (>=2.0.0rc4,<3.0.0) ; extra == "readthedocs"
Requires-Dist: sqlalchemy (>=1.4.50,<1.5.0)
Requires-Dist: sqlalchemy-migrate-hotoffthehamster (>0)
Requires-Dist: tomli (>=2.0.1) ; extra == "readthedocs"
Project-URL: documentation, https://nark.readthedocs.io/en/latest
Project-URL: download, https://pypi.org/project/nark/#files
Project-URL: homepage, https://github.com/doblabs/nark#👮
Project-URL: history, https://github.com/doblabs/nark/blob/release/HISTORY.rst
Project-URL: issues, https://github.com/doblabs/nark/issues
